{
  "fetched_at": 1766133600,
  "placeId": 109983668079237,
  "servers": [
    {
      "id": "48ff8ed0-e964-45b2-a92e-16f372ec33a5",
      "playing": 1,
      "maxPlayers": 8,
      "created": null
    },
    {
      "id": "52e81f04-8517-4c69-bd20-3ec45069c051",
      "playing": 1,
      "maxPlayers": 8,
      "created": null
    },
    {
      "id": "e55acdd5-dcbd-43e4-b61f-36fe7968a755",
      "playing": 1,
      "maxPlayers": 8,
      "created": null
    },
    {
      "id": "394145d5-7466-4f17-a5ca-9acbed2004f3",
      "playing": 1,
      "maxPlayers": 8,
      "created": null
    },
    {
      "id": "a7063e2a-498e-4139-aa50-e57a07687dc4",
      "playing": 1,
      "maxPlayers": 8,
      "created": null
    },
    {
      "id": "6afff61e-f1c7-430e-ab35-b6b52e9e045f",
      "playing": 1,
      "maxPlayers": 8,
      "created": null
    },
    {
      "id": "10df125e-665a-440f-a42b-af2da5473e66",
      "playing": 1,
      "maxPlayers": 8,
      "created": null
    },
    {
      "id": "7a02c96f-72b2-454c-8c5e-eade49e34128",
      "playing": 1,
      "maxPlayers": 8,
      "created": null
    },
    {
      "id": "e99f2ac6-4fdc-497f-a526-601df356ccb4",
      "playing": 1,
      "maxPlayers": 8,
      "created": null
    },
    {
      "id": "59a0697f-b6fb-4e8d-90d6-8950966329f3",
      "playing": 1,
      "maxPlayers": 8,
      "created": null
    },
    {
      "id": "8cc8120d-a420-4bc0-882a-67e6204ca930",
      "playing": 1,
      "maxPlayers": 8,
      "created": null
    },
    {
      "id": "802993a0-2041-429d-ac2c-56bc93cd5278",
      "playing": 1,
      "maxPlayers": 8,
      "created": null
    },
    {
      "id": "ec104b75-06eb-463c-9bf0-eebab5da90ff",
      "playing": 1,
      "maxPlayers": 8,
      "created": null
    },
    {
      "id": "c9f97f41-789b-45ee-b1ef-7c4e6b942628",
      "playing": 1,
      "maxPlayers": 8,
      "created": null
    },
    {
      "id": "4b6abfb4-02c2-4649-935d-83493b2ba487",
      "playing": 1,
      "maxPlayers": 8,
      "created": null
    },
    {
      "id": "79fb01ab-d2b8-4b62-83f4-c8325994d494",
      "playing": 1,
      "maxPlayers": 8,
      "created": null
    },
    {
      "id": "69a381f3-684a-48bf-bdff-fff3f5de8cd1",
      "playing": 1,
      "maxPlayers": 8,
      "created": null
    },
    {
      "id": "4f5e1071-1041-45c7-81a5-d2ca3a3381c9",
      "playing": 1,
      "maxPlayers": 8,
      "created": null
    },
    {
      "id": "51d24059-cdc3-45af-b097-ba21fff833ac",
      "playing": 1,
      "maxPlayers": 8,
      "created": null
    },
    {
      "id": "a11768e4-79bd-4d82-baed-8f8fb3c25394",
      "playing": 1,
      "maxPlayers": 8,
      "created": null
    },
    {
      "id": "79319acd-9e9e-4e5f-ba8c-75981fc32f9c",
      "playing": 1,
      "maxPlayers": 8,
      "created": null
    },
    {
      "id": "6efb51c1-936b-4ae9-bedb-6ea95a4a8ef1",
      "playing": 1,
      "maxPlayers": 8,
      "created": null
    },
    {
      "id": "fe9a8f02-c724-4ad8-ac2c-5fe73601b4b5",
      "playing": 1,
      "maxPlayers": 8,
      "created": null
    },
    {
      "id": "330f7970-1c18-466f-93fa-5cd5dc312d1b",
      "playing": 1,
      "maxPlayers": 8,
      "created": null
    },
    {
      "id": "b946b81d-1f79-4254-b889-55b086964ad8",
      "playing": 1,
      "maxPlayers": 8,
      "created": null
    },
    {
      "id": "80e4ae3e-d9d9-4b51-a146-91bc00ffbe73",
      "playing": 1,
      "maxPlayers": 8,
      "created": null
    },
    {
      "id": "1357592c-7258-409b-80bd-6a3c781753ef",
      "playing": 1,
      "maxPlayers": 8,
      "created": null
    },
    {
      "id": "bdb1eabe-c1b2-4b6f-925f-48efcaae4577",
      "playing": 1,
      "maxPlayers": 8,
      "created": null
    },
    {
      "id": "bb0cc203-dbd8-42a6-9fa5-d75f66a1d580",
      "playing": 1,
      "maxPlayers": 8,
      "created": null
    },
    {
      "id": "358feaea-7708-454a-848a-314ae465edf8",
      "playing": 1,
      "maxPlayers": 8,
      "created": null
    },
    {
      "id": "bd94d01d-4814-47f6-b86b-d0d8a3fb0023",
      "playing": 1,
      "maxPlayers": 8,
      "created": null
    },
    {
      "id": "99f9e1bb-da1e-4b05-9774-def775cef835",
      "playing": 1,
      "maxPlayers": 8,
      "created": null
    },
    {
      "id": "e68cc3c1-7782-47a9-a21f-7b8f01eb54b1",
      "playing": 1,
      "maxPlayers": 8,
      "created": null
    },
    {
      "id": "d91ce4fd-4f2f-4d58-9a91-f4fda59e4323",
      "playing": 1,
      "maxPlayers": 8,
      "created": null
    },
    {
      "id": "88748143-404b-4836-bc11-e92c097a0fb9",
      "playing": 1,
      "maxPlayers": 8,
      "created": null
    },
    {
      "id": "db2d2932-5daa-4bd7-97be-8fb02fd9fc89",
      "playing": 1,
      "maxPlayers": 8,
      "created": null
    },
    {
      "id": "ec859d3a-addc-48ce-a0a9-92f53cb8174d",
      "playing": 1,
      "maxPlayers": 8,
      "created": null
    },
    {
      "id": "a550d529-b730-4276-85f8-f4558b2c9dac",
      "playing": 1,
      "maxPlayers": 8,
      "created": null
    },
    {
      "id": "f559eaae-ca42-4a49-b307-ba231132a7da",
      "playing": 1,
      "maxPlayers": 8,
      "created": null
    },
    {
      "id": "f4ba5354-2240-44ae-a798-8a9215c9f814",
      "playing": 1,
      "maxPlayers": 8,
      "created": null
    },
    {
      "id": "fb585ccb-1fa1-41ce-8528-7064216cc917",
      "playing": 1,
      "maxPlayers": 8,
      "created": null
    },
    {
      "id": "19a7b54c-ef1a-40d5-8c8e-2b638e13958b",
      "playing": 1,
      "maxPlayers": 8,
      "created": null
    },
    {
      "id": "ab913b87-b0f0-4991-967e-b284e02e14f0",
      "playing": 1,
      "maxPlayers": 8,
      "created": null
    },
    {
      "id": "7a3ec2f6-0ac7-4979-8ac9-91c9a2fd873b",
      "playing": 1,
      "maxPlayers": 8,
      "created": null
    },
    {
      "id": "a17485cf-a4a3-45af-854d-943adb6dd28e",
      "playing": 1,
      "maxPlayers": 8,
      "created": null
    },
    {
      "id": "32c0b8d0-5e83-4a3d-98a4-65cb1abeb350",
      "playing": 1,
      "maxPlayers": 8,
      "created": null
    },
    {
      "id": "936448f2-e026-43e3-a45e-2d278116c30f",
      "playing": 1,
      "maxPlayers": 8,
      "created": null
    },
    {
      "id": "3cfae8ff-d6d6-4815-8799-91e94fd37335",
      "playing": 1,
      "maxPlayers": 8,
      "created": null
    },
    {
      "id": "4ee2d46b-d313-4bfb-938b-2a95a58d6dc8",
      "playing": 1,
      "maxPlayers": 8,
      "created": null
    },
    {
      "id": "567efd20-2951-49a7-b0ca-2474632babb1",
      "playing": 1,
      "maxPlayers": 8,
      "created": null
    },
    {
      "id": "0cb91ef5-1d4f-4766-adc3-9dadf94dc239",
      "playing": 1,
      "maxPlayers": 8,
      "created": null
    },
    {
      "id": "53c4e962-2619-4de6-8d1c-c01f4b6ee56d",
      "playing": 1,
      "maxPlayers": 8,
      "created": null
    },
    {
      "id": "baff3ac5-28f8-4b73-a631-7551667e067c",
      "playing": 1,
      "maxPlayers": 8,
      "created": null
    },
    {
      "id": "d7d0a8b1-48da-4e77-bdd1-0307e025ab8d",
      "playing": 1,
      "maxPlayers": 8,
      "created": null
    },
    {
      "id": "7428718c-62e9-4f95-8bcf-0f8dc9e7074d",
      "playing": 1,
      "maxPlayers": 8,
      "created": null
    },
    {
      "id": "ec180531-be2a-4f42-8680-15ae5c5fe72c",
      "playing": 1,
      "maxPlayers": 8,
      "created": null
    },
    {
      "id": "b16edd62-bd5b-471f-83f2-73e2ac57fd45",
      "playing": 1,
      "maxPlayers": 8,
      "created": null
    },
    {
      "id": "84b76608-eeba-4776-b53b-20c8075076ca",
      "playing": 1,
      "maxPlayers": 8,
      "created": null
    },
    {
      "id": "35078852-e9b1-4c94-842b-7afdddde7b8f",
      "playing": 1,
      "maxPlayers": 8,
      "created": null
    },
    {
      "id": "fb68d12f-0c0d-4f5f-85ae-e38dfbe25b42",
      "playing": 1,
      "maxPlayers": 8,
      "created": null
    },
    {
      "id": "d61c40b3-beaa-4321-923a-7028bd327276",
      "playing": 1,
      "maxPlayers": 8,
      "created": null
    },
    {
      "id": "124346f9-12b8-47a0-aa8c-dcaa95809096",
      "playing": 1,
      "maxPlayers": 8,
      "created": null
    },
    {
      "id": "e5f3bb46-4074-48d9-aef4-cb09178215fa",
      "playing": 1,
      "maxPlayers": 8,
      "created": null
    },
    {
      "id": "5404ee5d-4f53-4d03-8f73-3236b0338a53",
      "playing": 1,
      "maxPlayers": 8,
      "created": null
    },
    {
      "id": "9fb04d50-20e7-4aea-8081-db72a2535cf3",
      "playing": 1,
      "maxPlayers": 8,
      "created": null
    },
    {
      "id": "6b43d9ad-9558-46b0-951f-f6bd68ee67bf",
      "playing": 1,
      "maxPlayers": 8,
      "created": null
    },
    {
      "id": "1f6b699d-8732-41f3-a4cc-d70dc386ccac",
      "playing": 1,
      "maxPlayers": 8,
      "created": null
    },
    {
      "id": "7747a46b-ad13-411c-8072-348a526e48e3",
      "playing": 1,
      "maxPlayers": 8,
      "created": null
    },
    {
      "id": "f6587d97-815a-4575-be2b-9a68e431b9e1",
      "playing": 1,
      "maxPlayers": 8,
      "created": null
    },
    {
      "id": "025b4cdf-471e-492b-be42-972dfe28882b",
      "playing": 1,
      "maxPlayers": 8,
      "created": null
    },
    {
      "id": "ef752c78-656f-4736-80e6-05cae4a62df0",
      "playing": 1,
      "maxPlayers": 8,
      "created": null
    },
    {
      "id": "bb08d4ae-72a1-4559-bc0d-a2af130e1a22",
      "playing": 1,
      "maxPlayers": 8,
      "created": null
    },
    {
      "id": "e5e574b3-b7f2-483e-9820-6ea95dbfbe7b",
      "playing": 1,
      "maxPlayers": 8,
      "created": null
    },
    {
      "id": "2d549775-3cc3-4233-a5be-f648a320e193",
      "playing": 1,
      "maxPlayers": 8,
      "created": null
    },
    {
      "id": "d7b9c33c-01c5-48bd-a616-c8d9f9e1da67",
      "playing": 1,
      "maxPlayers": 8,
      "created": null
    },
    {
      "id": "da6fee7c-642f-486a-bac7-7abaa126084e",
      "playing": 1,
      "maxPlayers": 8,
      "created": null
    },
    {
      "id": "7414924d-1192-4135-ab6d-e01d451bd9c7",
      "playing": 1,
      "maxPlayers": 8,
      "created": null
    },
    {
      "id": "07b41aea-822e-4c54-ae2f-b52c6e471372",
      "playing": 1,
      "maxPlayers": 8,
      "created": null
    },
    {
      "id": "361891ed-ea30-4cfc-af49-ac6aba2b432c",
      "playing": 1,
      "maxPlayers": 8,
      "created": null
    },
    {
      "id": "27a8ef1e-8e23-48aa-8630-1a978acdacdd",
      "playing": 1,
      "maxPlayers": 8,
      "created": null
    },
    {
      "id": "789754d5-22db-442e-aa76-1fa575f8474e",
      "playing": 1,
      "maxPlayers": 8,
      "created": null
    },
    {
      "id": "15eb3487-5ff2-4c2f-b135-510723f1e55f",
      "playing": 1,
      "maxPlayers": 8,
      "created": null
    },
    {
      "id": "b0ba4c81-04f6-4e1a-ad1f-9bdb7bd570e9",
      "playing": 1,
      "maxPlayers": 8,
      "created": null
    },
    {
      "id": "584a01d7-6860-438d-83dd-e8a16e94441f",
      "playing": 1,
      "maxPlayers": 8,
      "created": null
    },
    {
      "id": "92105fcd-af21-49e7-91ab-b3be54cb4867",
      "playing": 2,
      "maxPlayers": 8,
      "created": null
    },
    {
      "id": "0a10077a-1598-4630-acaa-51c2b47e9be4",
      "playing": 2,
      "maxPlayers": 8,
      "created": null
    },
    {
      "id": "fc05f8b1-6a3a-4603-9c9b-da62f4a6a1ee",
      "playing": 2,
      "maxPlayers": 8,
      "created": null
    },
    {
      "id": "5b86f93a-c724-4603-a00c-8e5994b1fb78",
      "playing": 2,
      "maxPlayers": 8,
      "created": null
    },
    {
      "id": "aafa8686-f6cd-4a02-b9f3-5b34e9386491",
      "playing": 2,
      "maxPlayers": 8,
      "created": null
    },
    {
      "id": "80e0c09f-b300-4f76-9c55-055bfedeed27",
      "playing": 2,
      "maxPlayers": 8,
      "created": null
    },
    {
      "id": "9cfc5eb5-3add-4711-98a8-13b7df43127c",
      "playing": 2,
      "maxPlayers": 8,
      "created": null
    },
    {
      "id": "74cd60b1-b352-4008-a705-25d8b7bf3f3a",
      "playing": 2,
      "maxPlayers": 8,
      "created": null
    },
    {
      "id": "655517c2-f031-43c4-8101-065cf420685f",
      "playing": 2,
      "maxPlayers": 8,
      "created": null
    },
    {
      "id": "843bafc6-81f5-4e11-900d-1ae023e78a64",
      "playing": 2,
      "maxPlayers": 8,
      "created": null
    },
    {
      "id": "4208adb2-6bf8-4497-8cd5-fcb6f97086b9",
      "playing": 2,
      "maxPlayers": 8,
      "created": null
    },
    {
      "id": "76c32ca6-a616-4a1c-ae90-17fdd45c5d0e",
      "playing": 2,
      "maxPlayers": 8,
      "created": null
    },
    {
      "id": "3d68fea0-3760-47e4-bc33-b05b3afc0786",
      "playing": 2,
      "maxPlayers": 8,
      "created": null
    },
    {
      "id": "ab2dad3c-6e2e-4521-98b0-8a0b9fd2db9c",
      "playing": 2,
      "maxPlayers": 8,
      "created": null
    },
    {
      "id": "747bc7a8-81c8-4d50-9f66-514356dca5f5",
      "playing": 2,
      "maxPlayers": 8,
      "created": null
    },
    {
      "id": "3b2b8e4a-880e-4fd7-9b19-880837a47ff7",
      "playing": 2,
      "maxPlayers": 8,
      "created": null
    }
  ]
}